langchain_xbaza/__init__.py
langchain_xbaza/tools.py
langchain_xbaza-0.1.0.dist-info/licenses/LICENSE
langchain_xbaza-0.1.0.dist-info/METADATA
langchain_xbaza-0.1.0.dist-info/WHEEL
langchain_xbaza-0.1.0.dist-info/top_level.txt
langchain_xbaza-0.1.0.dist-info/RECORD
