Metadata-Version: 2.4
Name: langchain-xbaza
Version: 0.1.0
Summary: LangChain integration for Xbaza Belarus Job Market API
Home-page: https://github.com/LabelMinsk/langchain-xbaza
Author: Xbaza Team
Author-email: Xbaza Team <ai@xbaza.by>
License-Expression: MIT
Project-URL: Homepage, https://github.com/LabelMinsk/langchain-xbaza
Project-URL: Documentation, https://github.com/LabelMinsk/langchain-xbaza#readme
Project-URL: Repository, https://github.com/youruseLabelMinskrname/langchain-xbaza
Project-URL: Issues, https://github.com/LabelMinsk/langchain-xbaza/issues
Keywords: langchain,xbaza,belarus,job-market,api,ai
Classifier: Development Status :: 4 - Beta
Classifier: Intended Audience :: Developers
Classifier: Programming Language :: Python :: 3
Classifier: Programming Language :: Python :: 3.8
Classifier: Programming Language :: Python :: 3.9
Classifier: Programming Language :: Python :: 3.10
Classifier: Programming Language :: Python :: 3.11
Classifier: Topic :: Software Development :: Libraries :: Python Modules
Requires-Python: >=3.8
License-File: LICENSE
Requires-Dist: langchain>=0.1.0
Requires-Dist: langchain-core>=0.1.0
Requires-Dist: requests>=2.31.0
Provides-Extra: dev
Requires-Dist: pytest>=7.0.0; extra == "dev"
Requires-Dist: pytest-cov>=4.0.0; extra == "dev"
Requires-Dist: black>=23.0.0; extra == "dev"
Requires-Dist: ruff>=0.1.0; extra == "dev"
Dynamic: author
Dynamic: home-page
Dynamic: license-file
Dynamic: requires-python
